cli/__init__.py
cli/core.py
cli/initialise.py
cli/logging/FileHandler.py
cli/logging/__init__.py
cli/logging/initialise.py
cli/logging/levels.py
cli/logging/logmanager.py
cli/utils/__init__.py
cli/utils/color_utils.py
cli/utils/time_utils.py
cli_log-1.1.dist-info/LICENSE
cli_log-1.1.dist-info/METADATA
cli_log-1.1.dist-info/WHEEL
cli_log-1.1.dist-info/top_level.txt
cli_log-1.1.dist-info/RECORD
