Metadata-Version: 2.1
Name: cli-log
Version: 1.1
Summary: Command line interface logging.
Home-page: https://deltabotics.github.io/cli-log
Author: DeltaBotics
License: MIT
Project-URL: Source, https://github.com/DeltaBotics/cli-log
Keywords: logging
Classifier: Intended Audience :: Developers
Classifier: Topic :: System :: Logging
Classifier: License :: OSI Approved :: MIT License
Classifier: Operating System :: OS Independent
Classifier: Programming Language :: Python :: 3
License-File: LICENSE
Requires-Dist: colorama ==0.4.6
